cka/__init__.py
cka/cka.py
cka/hsic.py
cka/viz.py
pytorch_cka-1.0.0.dist-info/METADATA
pytorch_cka-1.0.0.dist-info/WHEEL
pytorch_cka-1.0.0.dist-info/licenses/LICENSE
pytorch_cka-1.0.0.dist-info/RECORD
