Metadata-Version: 2.4
Name: pytorch_cka
Version: 1.0.0
Summary: Centered Kernel Alignment (CKA) with Efficient Computation and Layer-wise Visualization for PyTorch 
Project-URL: Homepage, https://github.com/ryusudol/Centered-Kernel-Alignment
Project-URL: Repository, https://github.com/ryusudol/Centered-Kernel-Alignment
Project-URL: Issues, https://github.com/ryusudol/Centered-Kernel-Alignment/issues
Author-email: "Suhyeon (Sean) Yu" <suhyeon.yu.2789@gmail.com>
License: MIT License
License-File: LICENSE
Keywords: centered kernel alignment,cka,machine learning,neural networks,pytorch,representation,similarity
Classifier: Development Status :: 3 - Alpha
Classifier: Intended Audience :: Science/Research
Classifier: License :: OSI Approved :: MIT License
Classifier: Programming Language :: Python :: 3
Classifier: Programming Language :: Python :: 3.10
Classifier: Programming Language :: Python :: 3.11
Classifier: Programming Language :: Python :: 3.12
Classifier: Programming Language :: Python :: 3.13
Classifier: Programming Language :: Python :: 3.14
Classifier: Topic :: Scientific/Engineering :: Artificial Intelligence
Requires-Python: >=3.10
Requires-Dist: matplotlib>=3.5.0
Requires-Dist: numpy>=1.21.0
Requires-Dist: torch>=2.0.0
Requires-Dist: tqdm>=4.60.0
